neocrypto/Decrypt.py
neocrypto/DecryptedCharacterContainer.py
neocrypto/EncapsulationEquation.py
neocrypto/Encrypt.py
neocrypto/EncryptedCharacterContainer.py
neocrypto/Helpers.py
neocrypto/NeoCrypto.py
neocrypto/PrivateKey.py
neocrypto/PublicKey.py
neocrypto/StandardEquation.py
neocrypto/__init__.py
NeoCrypto-0.0.3a0.dist-info/LICENSE
NeoCrypto-0.0.3a0.dist-info/METADATA
NeoCrypto-0.0.3a0.dist-info/WHEEL
NeoCrypto-0.0.3a0.dist-info/top_level.txt
NeoCrypto-0.0.3a0.dist-info/RECORD
