Metadata-Version: 2.1
Name: NeoCrypto
Version: 0.0.3a0
Summary: post quantum asymetric cryptography package
Home-page: https://github.com/neomn/NeoCrypto
Author: Neo
Author-email: neomn110@gmail.com
License: GNU General Public License v3 (GPLv3)
Classifier: License :: OSI Approved :: GNU General Public License v3 (GPLv3)
Classifier: Programming Language :: Python :: 3.10
Classifier: Operating System :: OS Independent
Requires-Python: >=3.10
License-File: LICENSE
Provides-Extra: dev
Requires-Dist: pytest >=7.0 ; extra == 'dev'
Requires-Dist: twine >=4.0.2 ; extra == 'dev'
